watchtoken/__init__.py
watchtoken/counter.py
watchtoken/exceptions.py
watchtoken/loggers.py
watchtoken/models.py
watchtoken/utils.py
watchtoken/adapters/__init__.py
watchtoken/adapters/anthropic.py
watchtoken/adapters/google.py
watchtoken/adapters/mistral.py
watchtoken/adapters/openai.py
watchtoken-0.2.2.dist-info/licenses/LICENSE
watchtoken-0.2.2.dist-info/METADATA
watchtoken-0.2.2.dist-info/WHEEL
watchtoken-0.2.2.dist-info/top_level.txt
watchtoken-0.2.2.dist-info/RECORD
