Metadata-Version: 2.4
Name: watchtoken
Version: 0.2.2
Summary: A Python library for tracking and controlling token usage in LLM prompts without running the models
Author-email: Kuba <kuba@kamionka.eu>
License: MIT
Project-URL: Homepage, https://github.com/Kvmyk/Watchtoken
Project-URL: Repository, https://github.com/Kvmyk/Watchtoken
Project-URL: Issues, https://github.com/Kvmyk/Watchtoken/issues
Project-URL: Documentation, https://github.com/Kvmyk/Watchtoken#readme
Keywords: llm,tokens,openai,claude,gemini,cost-estimation
Classifier: Development Status :: 3 - Alpha
Classifier: Intended Audience :: Developers
Classifier: License :: OSI Approved :: MIT License
Classifier: Programming Language :: Python :: 3
Classifier: Programming Language :: Python :: 3.8
Classifier: Programming Language :: Python :: 3.9
Classifier: Programming Language :: Python :: 3.10
Classifier: Programming Language :: Python :: 3.11
Classifier: Programming Language :: Python :: 3.12
Classifier: Topic :: Software Development :: Libraries :: Python Modules
Classifier: Topic :: Scientific/Engineering :: Artificial Intelligence
Requires-Python: >=3.8
License-File: LICENSE
Requires-Dist: tiktoken>=0.5.0
Requires-Dist: pydantic>=2.0.0
Requires-Dist: typing-extensions>=4.0.0
Provides-Extra: dev
Requires-Dist: pytest>=7.0.0; extra == "dev"
Requires-Dist: pytest-cov>=4.0.0; extra == "dev"
Requires-Dist: black>=23.0.0; extra == "dev"
Requires-Dist: isort>=5.0.0; extra == "dev"
Requires-Dist: flake8>=6.0.0; extra == "dev"
Requires-Dist: mypy>=1.0.0; extra == "dev"
Provides-Extra: sentencepiece
Requires-Dist: sentencepiece>=0.1.99; extra == "sentencepiece"
Provides-Extra: transformers
Requires-Dist: transformers>=4.20.0; extra == "transformers"
Dynamic: license-file
